<?xml version="1.0" encoding="UTF-8" standalone="yes"?>
<imgdir name="2400255.img">
<imgdir name="info">
<int name="level" value="195"/>
<int name="bodyAttack" value="1"/>
<int name="maxMP" value="30000"/>
<int name="speed" value="5"/>
<int name="PDDamage" value="100"/>
<int name="PDRate" value="30"/>
<int name="MDDamage" value="100"/>
<int name="MDRate" value="30"/>
<int name="acc" value="723"/>
<int name="eva" value="205"/>
<int name="pushed" value="9000"/>
<int name="summonType" value="1"/>
<int name="category" value="8"/>
<string name="mobType" value="15N"/>
<float name="fs" value="10.0"/>
<int name="firstAttack" value="1"/>
<int name="exp" value="191100"/>
<int name="maxHP" value="35100000"/>
<int name="PADamage" value="925"/>
<int name="MADamage" value="1250"/>
</imgdir>
<imgdir name="stand">
<canvas name="0" width="132" height="140">
<vector name="origin" x="38" y="140"/>
<int name="z" value="0"/>
<int name="delay" value="120"/>
<vector name="lt" x="-37" y="-133"/>
<vector name="rb" x="82" y="2"/>
<vector name="head" x="4" y="-76"/>
</canvas>
<canvas name="1" width="132" height="139">
<vector name="origin" x="37" y="139"/>
<int name="z" value="0"/>
<int name="delay" value="120"/>
<vector name="lt" x="-37" y="-133"/>
<vector name="rb" x="82" y="2"/>
<vector name="head" x="4" y="-76"/>
</canvas>
<canvas name="2" width="131" height="138">
<vector name="origin" x="36" y="138"/>
<int name="z" value="0"/>
<int name="delay" value="120"/>
<vector name="lt" x="-37" y="-133"/>
<vector name="rb" x="82" y="2"/>
<vector name="head" x="4" y="-76"/>
</canvas>
<canvas name="3" width="130" height="139">
<vector name="origin" x="35" y="139"/>
<int name="z" value="0"/>
<int name="delay" value="120"/>
<vector name="lt" x="-37" y="-133"/>
<vector name="rb" x="82" y="2"/>
<vector name="head" x="4" y="-76"/>
</canvas>
<canvas name="4" width="130" height="140">
<vector name="origin" x="36" y="140"/>
<int name="z" value="0"/>
<int name="delay" value="120"/>
<vector name="lt" x="-37" y="-133"/>
<vector name="rb" x="82" y="2"/>
<vector name="head" x="4" y="-76"/>
</canvas>
<canvas name="5" width="129" height="141">
<vector name="origin" x="37" y="141"/>
<int name="z" value="0"/>
<int name="delay" value="120"/>
<vector name="lt" x="-37" y="-133"/>
<vector name="rb" x="82" y="2"/>
<vector name="head" x="4" y="-76"/>
</canvas>
</imgdir>
<imgdir name="move">
<canvas name="0" width="132" height="141">
<vector name="origin" x="39" y="141"/>
<int name="z" value="0"/>
<int name="delay" value="120"/>
<vector name="lt" x="-37" y="-133"/>
<vector name="rb" x="82" y="2"/>
<vector name="head" x="4" y="-76"/>
</canvas>
<canvas name="1" width="129" height="143">
<vector name="origin" x="38" y="143"/>
<int name="z" value="0"/>
<int name="delay" value="120"/>
<vector name="lt" x="-37" y="-133"/>
<vector name="rb" x="82" y="2"/>
<vector name="head" x="4" y="-76"/>
</canvas>
<canvas name="2" width="130" height="140">
<vector name="origin" x="36" y="140"/>
<int name="z" value="0"/>
<int name="delay" value="120"/>
<vector name="lt" x="-37" y="-133"/>
<vector name="rb" x="82" y="2"/>
<vector name="head" x="4" y="-76"/>
</canvas>
<canvas name="3" width="126" height="141">
<vector name="origin" x="35" y="141"/>
<int name="z" value="0"/>
<int name="delay" value="120"/>
<vector name="lt" x="-37" y="-133"/>
<vector name="rb" x="82" y="2"/>
<vector name="head" x="4" y="-76"/>
</canvas>
<canvas name="4" width="124" height="143">
<vector name="origin" x="35" y="143"/>
<int name="z" value="0"/>
<int name="delay" value="120"/>
<vector name="lt" x="-37" y="-133"/>
<vector name="rb" x="82" y="2"/>
<vector name="head" x="4" y="-76"/>
</canvas>
<canvas name="5" width="131" height="140">
<vector name="origin" x="37" y="140"/>
<int name="z" value="0"/>
<int name="delay" value="120"/>
<vector name="lt" x="-37" y="-133"/>
<vector name="rb" x="82" y="2"/>
<vector name="head" x="4" y="-76"/>
</canvas>
</imgdir>
<imgdir name="attack1">
<imgdir name="info">
<imgdir name="range">
<vector name="lt" x="-350" y="-180"/>
<vector name="rb" x="95" y="20"/>
</imgdir>
<imgdir name="hit">
<canvas name="0" width="120" height="181">
<vector name="origin" x="64" y="91"/>
<int name="z" value="0"/>
<int name="delay" value="120"/>
</canvas>
<canvas name="1" width="114" height="127">
<vector name="origin" x="55" y="64"/>
<int name="z" value="0"/>
<int name="delay" value="120"/>
</canvas>
<canvas name="2" width="115" height="98">
<vector name="origin" x="57" y="57"/>
<int name="z" value="0"/>
<int name="delay" value="120"/>
</canvas>
<canvas name="3" width="35" height="59">
<vector name="origin" x="15" y="34"/>
<int name="z" value="0"/>
<int name="delay" value="120"/>
</canvas>
</imgdir>
<int name="attackAfter" value="960"/>
<int name="action" value="1"/>
<int name="attackRatio" value="100"/>
<int name="type" value="0"/>
</imgdir>
<canvas name="0" width="132" height="141">
<vector name="origin" x="38" y="141"/>
<int name="z" value="0"/>
<int name="delay" value="120"/>
<vector name="lt" x="-37" y="-133"/>
<vector name="rb" x="82" y="2"/>
<vector name="head" x="4" y="-76"/>
</canvas>
<canvas name="1" width="132" height="139">
<vector name="origin" x="35" y="139"/>
<int name="z" value="0"/>
<int name="delay" value="120"/>
<vector name="lt" x="-37" y="-133"/>
<vector name="rb" x="82" y="2"/>
<vector name="head" x="5" y="-76"/>
</canvas>
<canvas name="2" width="132" height="137">
<vector name="origin" x="31" y="137"/>
<int name="z" value="0"/>
<int name="delay" value="120"/>
<vector name="lt" x="-37" y="-133"/>
<vector name="rb" x="87" y="2"/>
<vector name="head" x="7" y="-78"/>
</canvas>
<canvas name="3" width="152" height="105">
<vector name="origin" x="28" y="105"/>
<int name="z" value="0"/>
<int name="delay" value="120"/>
<vector name="lt" x="-28" y="-104"/>
<vector name="rb" x="113" y="2"/>
<vector name="head" x="11" y="-80"/>
</canvas>
<canvas name="4" width="169" height="131">
<vector name="origin" x="57" y="118"/>
<int name="z" value="0"/>
<int name="delay" value="120"/>
<vector name="lt" x="-29" y="-106"/>
<vector name="rb" x="100" y="1"/>
<vector name="head" x="12" y="-82"/>
</canvas>
<canvas name="5" width="171" height="132">
<vector name="origin" x="60" y="118"/>
<int name="z" value="0"/>
<int name="delay" value="120"/>
<vector name="lt" x="-26" y="-105"/>
<vector name="rb" x="100" y="3"/>
<vector name="head" x="15" y="-82"/>
</canvas>
<canvas name="6" width="170" height="132">
<vector name="origin" x="60" y="118"/>
<int name="z" value="0"/>
<int name="delay" value="120"/>
<vector name="lt" x="-23" y="-106"/>
<vector name="rb" x="101" y="4"/>
<vector name="head" x="16" y="-83"/>
</canvas>
<canvas name="7" width="162" height="129">
<vector name="origin" x="57" y="115"/>
<int name="z" value="0"/>
<int name="delay" value="120"/>
<vector name="lt" x="-23" y="-106"/>
<vector name="rb" x="101" y="4"/>
<vector name="head" x="16" y="-83"/>
</canvas>
<canvas name="8" width="140" height="158">
<vector name="origin" x="68" y="119"/>
<int name="z" value="0"/>
<int name="delay" value="120"/>
<vector name="lt" x="-68" y="-112"/>
<vector name="rb" x="74" y="31"/>
<vector name="head" x="-9" y="-71"/>
</canvas>
<canvas name="9" width="314" height="197">
<vector name="origin" x="198" y="119"/>
<int name="z" value="0"/>
<int name="delay" value="120"/>
<vector name="lt" x="-158" y="-92"/>
<vector name="rb" x="39" y="5"/>
<vector name="head" x="-9" y="-71"/>
</canvas>
<canvas name="10" width="323" height="188">
<vector name="origin" x="192" y="113"/>
<int name="z" value="0"/>
<int name="delay" value="120"/>
<vector name="lt" x="-158" y="-92"/>
<vector name="rb" x="39" y="5"/>
<vector name="head" x="-9" y="-71"/>
</canvas>
<canvas name="11" width="368" height="175">
<vector name="origin" x="235" y="107"/>
<int name="z" value="0"/>
<int name="delay" value="120"/>
<vector name="lt" x="-158" y="-92"/>
<vector name="rb" x="39" y="5"/>
<vector name="head" x="-9" y="-71"/>
</canvas>
<canvas name="12" width="360" height="167">
<vector name="origin" x="225" y="107"/>
<int name="z" value="0"/>
<int name="delay" value="120"/>
<vector name="lt" x="-158" y="-92"/>
<vector name="rb" x="39" y="5"/>
<vector name="head" x="-9" y="-71"/>
</canvas>
<canvas name="13" width="279" height="140">
<vector name="origin" x="143" y="91"/>
<int name="z" value="0"/>
<int name="delay" value="120"/>
<vector name="lt" x="-158" y="-92"/>
<vector name="rb" x="39" y="5"/>
<vector name="head" x="-9" y="-71"/>
</canvas>
<canvas name="14" width="180" height="140">
<vector name="origin" x="143" y="91"/>
<int name="z" value="0"/>
<int name="delay" value="120"/>
<vector name="lt" x="-158" y="-92"/>
<vector name="rb" x="39" y="5"/>
<vector name="head" x="-9" y="-71"/>
</canvas>
<canvas name="15" width="141" height="107">
<vector name="origin" x="103" y="91"/>
<int name="z" value="0"/>
<int name="delay" value="120"/>
<vector name="lt" x="-94" y="-92"/>
<vector name="rb" x="39" y="5"/>
<vector name="head" x="-9" y="-71"/>
</canvas>
<canvas name="16" width="114" height="107">
<vector name="origin" x="66" y="91"/>
<int name="z" value="0"/>
<int name="delay" value="120"/>
<vector name="lt" x="-57" y="-92"/>
<vector name="rb" x="50" y="5"/>
<vector name="head" x="-9" y="-71"/>
</canvas>
<canvas name="17" width="163" height="102">
<vector name="origin" x="45" y="102"/>
<int name="z" value="0"/>
<int name="delay" value="120"/>
<vector name="lt" x="-47" y="-97"/>
<vector name="rb" x="104" y="2"/>
<vector name="head" x="-4" y="-71"/>
</canvas>
<canvas name="18" width="139" height="136">
<vector name="origin" x="40" y="136"/>
<int name="z" value="0"/>
<int name="delay" value="120"/>
<vector name="lt" x="-37" y="-133"/>
<vector name="rb" x="82" y="2"/>
<vector name="head" x="2" y="-76"/>
</canvas>
<uol name="19" value="../stand/0"/>
<uol name="20" value="../stand/1"/>
<uol name="21" value="../stand/2"/>
<uol name="22" value="../stand/3"/>
<uol name="23" value="../stand/4"/>
<uol name="24" value="../stand/5"/>
</imgdir>
<imgdir name="hit1">
<canvas name="0" width="158" height="140">
<vector name="origin" x="31" y="140"/>
<int name="z" value="0"/>
<int name="delay" value="600"/>
<vector name="lt" x="-17" y="-131"/>
<vector name="rb" x="116" y="1"/>
<vector name="head" x="26" y="-78"/>
</canvas>
</imgdir>
<imgdir name="die1">
<canvas name="0" width="132" height="141">
<vector name="origin" x="38" y="141"/>
<int name="z" value="0"/>
<int name="delay" value="120"/>
</canvas>
<canvas name="1" width="158" height="140">
<vector name="origin" x="31" y="140"/>
<int name="z" value="0"/>
<int name="delay" value="120"/>
</canvas>
<canvas name="2" width="164" height="140">
<vector name="origin" x="37" y="140"/>
<int name="z" value="0"/>
<int name="delay" value="120"/>
</canvas>
<canvas name="3" width="172" height="140">
<vector name="origin" x="40" y="140"/>
<int name="z" value="0"/>
<int name="delay" value="120"/>
</canvas>
<canvas name="4" width="131" height="138">
<vector name="origin" x="-1" y="138"/>
<int name="z" value="0"/>
<int name="delay" value="120"/>
</canvas>
<canvas name="5" width="131" height="138">
<vector name="origin" x="-2" y="138"/>
<int name="z" value="0"/>
<int name="delay" value="120"/>
</canvas>
<canvas name="6" width="121" height="124">
<vector name="origin" x="1" y="124"/>
<int name="z" value="0"/>
<int name="delay" value="120"/>
</canvas>
<canvas name="7" width="188" height="148">
<vector name="origin" x="66" y="121"/>
<int name="z" value="0"/>
<int name="delay" value="120"/>
</canvas>
<canvas name="8" width="236" height="154">
<vector name="origin" x="93" y="126"/>
<int name="z" value="0"/>
<int name="delay" value="120"/>
</canvas>
<canvas name="9" width="319" height="123">
<vector name="origin" x="114" y="100"/>
<int name="z" value="0"/>
<int name="delay" value="120"/>
</canvas>
<canvas name="10" width="333" height="116">
<vector name="origin" x="128" y="94"/>
<int name="z" value="0"/>
<int name="delay" value="120"/>
</canvas>
<canvas name="11" width="343" height="125">
<vector name="origin" x="139" y="100"/>
<int name="z" value="0"/>
<int name="delay" value="120"/>
</canvas>
<canvas name="12" width="357" height="116">
<vector name="origin" x="146" y="92"/>
<int name="z" value="0"/>
<int name="delay" value="120"/>
</canvas>
<canvas name="13" width="329" height="126">
<vector name="origin" x="109" y="102"/>
<int name="z" value="0"/>
<int name="delay" value="120"/>
</canvas>
<canvas name="14" width="34" height="127">
<vector name="origin" x="13" y="102"/>
<int name="z" value="0"/>
<int name="delay" value="120"/>
</canvas>
<canvas name="15" width="19" height="37">
<vector name="origin" x="13" y="55"/>
<int name="z" value="0"/>
<int name="delay" value="120"/>
</canvas>
</imgdir>
</imgdir>
