<?xml version="1.0" encoding="UTF-8" standalone="yes"?>
<imgdir name="3645301.img">
    <imgdir name="info">
        <int name="level" value="12"/>
        <int name="bodyAttack" value="1"/>
        <int name="maxHP" value="175"/>
        <int name="maxMP" value="20"/>
        <int name="speed" value="-30"/>
        <int name="PADamage" value="50"/>
        <int name="MADamage" value="45"/>
        <int name="PDRate" value="10"/>
        <int name="MDRate" value="10"/>
        <int name="acc" value="23"/>
        <int name="eva" value="1"/>
        <int name="pushed" value="20"/>
        <float name="fs" value="10.0"/>
        <int name="exp" value="21"/>
        <int name="summonType" value="1"/>
        <int name="category" value="1"/>
        <string name="mobType" value="1N"/>
        <int name="PDDamage" value="0"/>
        <int name="MDDamage" value="0"/>
        <int name="eva" value="0"/>
    </imgdir>
    <imgdir name="stand">
        <canvas name="0" width="55" height="41">
            <vector name="origin" x="30" y="40"/>
            <int name="z" value="0"/>
            <int name="delay" value="80"/>
            <vector name="lt" x="-30" y="-40"/>
            <vector name="rb" x="25" y="1"/>
            <vector name="head" x="-8" y="-40"/>
        </canvas>
        <canvas name="1" width="54" height="42">
            <vector name="origin" x="30" y="41"/>
            <int name="z" value="0"/>
            <int name="delay" value="80"/>
            <vector name="lt" x="-30" y="-40"/>
            <vector name="rb" x="25" y="1"/>
            <vector name="head" x="-8" y="-40"/>
        </canvas>
        <canvas name="2" width="55" height="41">
            <vector name="origin" x="30" y="40"/>
            <int name="z" value="0"/>
            <int name="delay" value="80"/>
            <vector name="lt" x="-30" y="-40"/>
            <vector name="rb" x="25" y="1"/>
            <vector name="head" x="-8" y="-40"/>
        </canvas>
        <canvas name="3" width="55" height="40">
            <vector name="origin" x="30" y="39"/>
            <int name="z" value="0"/>
            <int name="delay" value="80"/>
            <vector name="lt" x="-30" y="-40"/>
            <vector name="rb" x="25" y="1"/>
            <vector name="head" x="-8" y="-40"/>
        </canvas>
    </imgdir>
    <imgdir name="move">
        <canvas name="0" width="55" height="42">
            <vector name="origin" x="30" y="41"/>
            <int name="z" value="0"/>
            <int name="delay" value="80"/>
            <vector name="lt" x="-30" y="-40"/>
            <vector name="rb" x="25" y="1"/>
            <vector name="head" x="-8" y="-40"/>
        </canvas>
        <canvas name="1" width="55" height="41">
            <vector name="origin" x="30" y="40"/>
            <int name="z" value="0"/>
            <int name="delay" value="80"/>
            <vector name="lt" x="-30" y="-40"/>
            <vector name="rb" x="25" y="1"/>
            <vector name="head" x="-8" y="-40"/>
        </canvas>
        <canvas name="2" width="57" height="39">
            <vector name="origin" x="31" y="38"/>
            <int name="z" value="0"/>
            <int name="delay" value="80"/>
            <vector name="lt" x="-30" y="-40"/>
            <vector name="rb" x="25" y="1"/>
            <vector name="head" x="-8" y="-40"/>
        </canvas>
        <canvas name="3" width="56" height="40">
            <vector name="origin" x="30" y="40"/>
            <int name="z" value="0"/>
            <int name="delay" value="80"/>
            <vector name="lt" x="-30" y="-40"/>
            <vector name="rb" x="25" y="1"/>
            <vector name="head" x="-8" y="-40"/>
        </canvas>
        <canvas name="4" width="55" height="41">
            <vector name="origin" x="30" y="41"/>
            <int name="z" value="0"/>
            <int name="delay" value="80"/>
            <vector name="lt" x="-30" y="-40"/>
            <vector name="rb" x="25" y="1"/>
            <vector name="head" x="-8" y="-40"/>
        </canvas>
        <canvas name="5" width="54" height="42">
            <vector name="origin" x="30" y="41"/>
            <int name="z" value="0"/>
            <int name="delay" value="80"/>
            <vector name="lt" x="-30" y="-40"/>
            <vector name="rb" x="25" y="1"/>
            <vector name="head" x="-8" y="-40"/>
        </canvas>
    </imgdir>
    <imgdir name="hit1">
        <canvas name="0" width="66" height="45">
            <vector name="origin" x="30" y="45"/>
            <int name="z" value="0"/>
            <vector name="lt" x="-30" y="-40"/>
            <vector name="rb" x="25" y="1"/>
            <vector name="head" x="-8" y="-40"/>
        </canvas>
    </imgdir>
    <imgdir name="die1">
        <canvas name="0" width="55" height="41">
            <vector name="origin" x="30" y="40"/>
            <int name="z" value="0"/>
            <int name="delay" value="80"/>
        </canvas>
        <canvas name="1" width="66" height="45">
            <vector name="origin" x="30" y="45"/>
            <int name="z" value="0"/>
            <int name="delay" value="80"/>
        </canvas>
        <canvas name="2" width="72" height="43">
            <vector name="origin" x="32" y="43"/>
            <int name="z" value="0"/>
            <int name="delay" value="80"/>
        </canvas>
        <canvas name="3" width="73" height="41">
            <vector name="origin" x="31" y="41"/>
            <int name="z" value="0"/>
            <int name="delay" value="80"/>
        </canvas>
        <canvas name="4" width="56" height="41">
            <vector name="origin" x="13" y="41"/>
            <int name="z" value="0"/>
            <int name="delay" value="80"/>
        </canvas>
        <canvas name="5" width="56" height="41">
            <vector name="origin" x="12" y="41"/>
            <int name="z" value="0"/>
            <int name="delay" value="80"/>
        </canvas>
        <canvas name="6" width="74" height="38">
            <vector name="origin" x="20" y="36"/>
            <int name="z" value="0"/>
            <int name="delay" value="80"/>
        </canvas>
        <canvas name="7" width="85" height="39">
            <vector name="origin" x="23" y="37"/>
            <int name="z" value="0"/>
            <int name="delay" value="80"/>
        </canvas>
        <canvas name="8" width="87" height="40">
            <vector name="origin" x="24" y="37"/>
            <int name="z" value="0"/>
            <int name="delay" value="80"/>
        </canvas>
        <canvas name="9" width="88" height="39">
            <vector name="origin" x="24" y="36"/>
            <int name="z" value="0"/>
            <int name="delay" value="80"/>
        </canvas>
        <canvas name="10" width="89" height="39">
            <vector name="origin" x="25" y="36"/>
            <int name="z" value="0"/>
            <int name="delay" value="80"/>
        </canvas>
    </imgdir>
</imgdir>
