<?xml version="1.0" encoding="UTF-8" standalone="yes"?>
<imgdir name="8880012.img">
<imgdir name="hit1">
<canvas name="0" width="199" height="200">
<vector name="origin" x="104" y="179"/>
</canvas>
</imgdir>
<imgdir name="die1">
<canvas name="0" width="232" height="149">
<vector name="origin" x="108" y="148"/>
<int name="delay" value="120"/>
</canvas>
<canvas name="1" width="234" height="194">
<vector name="origin" x="106" y="193"/>
<int name="delay" value="120"/>
</canvas>
<canvas name="2" width="236" height="203">
<vector name="origin" x="107" y="202"/>
<int name="delay" value="120"/>
</canvas>
<canvas name="3" width="258" height="205">
<vector name="origin" x="116" y="204"/>
<int name="delay" value="120"/>
</canvas>
<canvas name="4" width="272" height="206">
<vector name="origin" x="122" y="205"/>
<int name="delay" value="120"/>
</canvas>
<canvas name="5" width="260" height="207">
<vector name="origin" x="116" y="207"/>
<int name="delay" value="120"/>
</canvas>
<canvas name="6" width="190" height="98">
<vector name="origin" x="88" y="98"/>
<int name="delay" value="120"/>
</canvas>
</imgdir>
<imgdir name="fly">
<canvas name="0" width="199" height="200">
<vector name="origin" x="104" y="179"/>
<int name="delay" value="120"/>
<vector name="lt" x="-89" y="-138"/>
<vector name="rb" x="90" y="0"/>
</canvas>
<canvas name="1" width="196" height="202">
<vector name="origin" x="97" y="174"/>
<int name="delay" value="120"/>
<vector name="rb" x="90" y="0"/>
<vector name="lt" x="-89" y="-138"/>
</canvas>
<canvas name="2" width="190" height="191">
<vector name="origin" x="87" y="163"/>
<int name="delay" value="120"/>
<vector name="rb" x="90" y="0"/>
<vector name="lt" x="-89" y="-138"/>
</canvas>
<canvas name="3" width="198" height="198">
<vector name="origin" x="94" y="171"/>
<int name="delay" value="120"/>
<vector name="rb" x="90" y="0"/>
<vector name="lt" x="-89" y="-138"/>
</canvas>
<canvas name="4" width="209" height="209">
<vector name="origin" x="98" y="178"/>
<int name="delay" value="120"/>
<vector name="rb" x="90" y="0"/>
<vector name="lt" x="-89" y="-138"/>
</canvas>
<canvas name="5" width="207" height="207">
<vector name="origin" x="102" y="178"/>
<int name="delay" value="120"/>
<vector name="rb" x="90" y="0"/>
<vector name="lt" x="-89" y="-138"/>
</canvas>
<canvas name="6" width="201" height="201">
<vector name="origin" x="103" y="177"/>
<int name="delay" value="120"/>
<vector name="rb" x="90" y="0"/>
<vector name="lt" x="-89" y="-138"/>
</canvas>
<canvas name="7" width="198" height="194">
<vector name="origin" x="110" y="181"/>
<int name="delay" value="120"/>
<vector name="rb" x="90" y="0"/>
<vector name="lt" x="-89" y="-138"/>
</canvas>
</imgdir>
<imgdir name="info">
<int name="level" value="1"/>
<int name="maxHP" value="1"/>
<int name="maxMP" value="1"/>
<int name="speed" value="0"/>
<int name="PADamage" value="8888"/>
<int name="PDDamage" value="0"/>
<int name="MADamage" value="0"/>
<int name="MDDamage" value="0"/>
<int name="acc" value="1"/>
<int name="eva" value="0"/>
<int name="exp" value="0"/>
<int name="undead" value="0"/>
<int name="pushed" value="0"/>
<float name="fs" value="10.0"/>
<int name="summonType" value="1"/>
<int name="boss" value="1"/>
<int name="noFlip" value="1"/>
<int name="invincible" value="1"/>
<int name="hideHP" value="1"/>
<int name="hideName" value="1"/>
<int name="bodyAttack" value="1"/>
<int name="flySpeed" value="-20"/>
<imgdir name="selfDestruction">
<int name="action" value="2"/>
<int name="hp" value="25000"/>
</imgdir>
</imgdir>
</imgdir>
